aminoraid.py
aminoraid-1.1.2.dist-info/WHEEL
aminoraid-1.1.2.dist-info/METADATA
aminoraid-1.1.2.dist-info/RECORD
