Metadata-Version: 2.1
Name: aminoraid
Version: 1.1.2
Summary: 
Author: Some Community
Author-email: olegskvorcovn1@gmail.com
Requires-Python: >=3.6,<4.0
Classifier: Programming Language :: Python :: 3
Classifier: Programming Language :: Python :: 3.6
Classifier: Programming Language :: Python :: 3.7
Classifier: Programming Language :: Python :: 3.8
Requires-Dist: Amino.py (==1.1.7)
